pdf2zh_next/__init__.py
pdf2zh_next/const.py
pdf2zh_next/gui.py
pdf2zh_next/gui_translation.yaml
pdf2zh_next/high_level.py
pdf2zh_next/http_api.py
pdf2zh_next/i18n.py
pdf2zh_next/main.py
pdf2zh_next/assets/powered_by_siliconflow_dark.png
pdf2zh_next/assets/powered_by_siliconflow_light.png
pdf2zh_next/config/__init__.py
pdf2zh_next/config/cli_env_model.py
pdf2zh_next/config/main.py
pdf2zh_next/config/model.py
pdf2zh_next/config/translate_engine_model.py
pdf2zh_next/translator/__init__.py
pdf2zh_next/translator/base_rate_limiter.py
pdf2zh_next/translator/base_translator.py
pdf2zh_next/translator/cache.py
pdf2zh_next/translator/utils.py
pdf2zh_next/translator/rate_limiter/qps_rate_limiter.py
pdf2zh_next/translator/translator_impl/anythingllm.py
pdf2zh_next/translator/translator_impl/azure.py
pdf2zh_next/translator/translator_impl/azureopenai.py
pdf2zh_next/translator/translator_impl/bing.py
pdf2zh_next/translator/translator_impl/claudecode.py
pdf2zh_next/translator/translator_impl/clitranslator.py
pdf2zh_next/translator/translator_impl/deepl.py
pdf2zh_next/translator/translator_impl/dify.py
pdf2zh_next/translator/translator_impl/google.py
pdf2zh_next/translator/translator_impl/ollama.py
pdf2zh_next/translator/translator_impl/openai.py
pdf2zh_next/translator/translator_impl/qwenmt.py
pdf2zh_next/translator/translator_impl/siliconflow.py
pdf2zh_next/translator/translator_impl/siliconflowfree.py
pdf2zh_next/translator/translator_impl/tencentmechinetranslation.py
pdf2zh_next/translator/translator_impl/xinference.py
pdf2zh_next/utils/asynchronize/__init__.py
pdf2zh_next-2.8.2.dist-info/METADATA
pdf2zh_next-2.8.2.dist-info/WHEEL
pdf2zh_next-2.8.2.dist-info/entry_points.txt
pdf2zh_next-2.8.2.dist-info/licenses/LICENSE
pdf2zh_next-2.8.2.dist-info/RECORD
