Metadata-Version: 2.4
Name: pdf2zh-next
Version: 2.8.2
Summary: PDF Translator based on BabelDOC
Project-URL: Homepage, https://github.com/PDFMathTranslate-next/PDFMathTranslate-next
Author-email: awwaawwa <aw@funstory.ai>
Maintainer-email: awwaawwa <aw@funstory.ai>
License-Expression: AGPL-3.0
License-File: LICENSE
Classifier: Operating System :: OS Independent
Classifier: Programming Language :: Python :: 3
Requires-Python: <3.14,>=3.10
Requires-Dist: azure-ai-translation-text<=1.0.1
Requires-Dist: babeldoc<0.6.0,>=0.5.20
Requires-Dist: chardet>=5.2.0
Requires-Dist: deepl
Requires-Dist: fastapi>=0.115.12
Requires-Dist: fonttools
Requires-Dist: gradio-i18n==0.3.4
Requires-Dist: gradio-pdf>=0.0.21
Requires-Dist: gradio<5.36
Requires-Dist: httpx>=0.28.1
Requires-Dist: legacy-cgi; python_version >= '3.13'
Requires-Dist: numpy
Requires-Dist: ollama
Requires-Dist: openai>=1.0.0
Requires-Dist: peewee>=3.17.8
Requires-Dist: pydantic-settings>=2.8.1
Requires-Dist: pydantic>=2.10.6
Requires-Dist: pymupdf<1.25.3
Requires-Dist: pyyaml>=6.0.2
Requires-Dist: requests
Requires-Dist: rich
Requires-Dist: sse-starlette>=2.3.3
Requires-Dist: tenacity
Requires-Dist: tencentcloud-sdk-python-tmt
Requires-Dist: tqdm
Requires-Dist: uvicorn>=0.34.2
Requires-Dist: xinference-client
